databudgie/__init__.py
databudgie/__main__.py
databudgie/api.py
databudgie/backup.py
databudgie/compression.py
databudgie/config.py
databudgie/match.py
databudgie/output.py
databudgie/py.typed
databudgie/restore.py
databudgie/s3.py
databudgie/storage.py
databudgie/table_op.py
databudgie/utils.py
databudgie/adapter/__init__.py
databudgie/adapter/base.py
databudgie/adapter/postgres.py
databudgie/cli/__init__.py
databudgie/cli/base.py
databudgie/cli/commands.py
databudgie/cli/config.py
databudgie/manifest/__init__.py
databudgie/manifest/manager.py
databudgie/manifest/sqlalchemy.py
databudgie-2.9.1.dist-info/METADATA
databudgie-2.9.1.dist-info/WHEEL
databudgie-2.9.1.dist-info/entry_points.txt
databudgie-2.9.1.dist-info/licenses/LICENSE
databudgie-2.9.1.dist-info/RECORD
