Metadata-Version: 2.4
Name: databudgie
Version: 2.9.1
Summary: Ergonomic and flexible tool for database backup and restore
Project-URL: Repository, https://github.com/schireson/databudgie
Author-email: Andrew Sosa <andrewso@known.is>, Dan Cardin <ddcardin@gmail.com>
License: MIT
License-File: LICENSE
Keywords: database,etl,postgres,s3,sqlalchemy
Classifier: License :: OSI Approved :: MIT License
Classifier: Topic :: System :: Archiving :: Backup
Requires-Python: <4,>=3.8
Requires-Dist: click>=7.0.0
Requires-Dist: configly[yaml]>=1.0.0
Requires-Dist: importlib-metadata; python_version < '3.8'
Requires-Dist: rich
Requires-Dist: sqlalchemy>=1.3
Requires-Dist: strapp[click,sqlalchemy]>=0.2.7
Requires-Dist: typing-extensions>=3.10.0; python_version < '3.8'
Provides-Extra: postgres
Requires-Dist: psycopg[binary]>=3.0; extra == 'postgres'
Provides-Extra: s3
Requires-Dist: boto3; extra == 's3'
